Workbook

Sheet Summary
A1: Wholesale ERP — Manual Test Cases
A3: Module | B3: Code | C3: Total | D3: Positive | E3: Negative | F3: Pass | G3: Fail | H3: Blocked | I3: Pending
A4: Products & Inventory | B4: PRD | C4: 65 | D4: 19 | E4: 46 | F4: =COUNTIF('PRD Products & Inventory'!$I:$I,"Pass") | G4: =COUNTIF('PRD Products & Inventory'!$I:$I,"Fail") | H4: =COUNTIF('PRD Products & Inventory'!$I:$I,"Blocked") | I4: =C4-F4-G4-H4
A5: Purchase | B5: PUR | C5: 52 | D5: 13 | E5: 39 | F5: =COUNTIF('PUR Purchase'!$I:$I,"Pass") | G5: =COUNTIF('PUR Purchase'!$I:$I,"Fail") | H5: =COUNTIF('PUR Purchase'!$I:$I,"Blocked") | I5: =C5-F5-G5-H5
A6: Billing & Sales | B6: BIL | C6: 56 | D6: 18 | E6: 38 | F6: =COUNTIF('BIL Billing & Sales'!$I:$I,"Pass") | G6: =COUNTIF('BIL Billing & Sales'!$I:$I,"Fail") | H6: =COUNTIF('BIL Billing & Sales'!$I:$I,"Blocked") | I6: =C6-F6-G6-H6
A7: Warehouse | B7: WH | C7: 64 | D7: 21 | E7: 43 | F7: =COUNTIF('WH Warehouse'!$I:$I,"Pass") | G7: =COUNTIF('WH Warehouse'!$I:$I,"Fail") | H7: =COUNTIF('WH Warehouse'!$I:$I,"Blocked") | I7: =C7-F7-G7-H7
A8: Accounting | B8: ACC | C8: 38 | D8: 18 | E8: 20 | F8: =COUNTIF('ACC Accounting'!$I:$I,"Pass") | G8: =COUNTIF('ACC Accounting'!$I:$I,"Fail") | H8: =COUNTIF('ACC Accounting'!$I:$I,"Blocked") | I8: =C8-F8-G8-H8
A9: GST / E-Invoice / E-Way Bill | B9: GST | C9: 46 | D9: 15 | E9: 31 | F9: =COUNTIF('GST GST E-Invoice E-Way Bill'!$I:$I,"Pass") | G9: =COUNTIF('GST GST E-Invoice E-Way Bill'!$I:$I,"Fail") | H9: =COUNTIF('GST GST E-Invoice E-Way Bill'!$I:$I,"Blocked") | I9: =C9-F9-G9-H9
A10: Reports & Dashboard | B10: RPT | C10: 39 | D10: 17 | E10: 22 | F10: =COUNTIF('RPT Reports & Dashboard'!$I:$I,"Pass") | G10: =COUNTIF('RPT Reports & Dashboard'!$I:$I,"Fail") | H10: =COUNTIF('RPT Reports & Dashboard'!$I:$I,"Blocked") | I10: =C10-F10-G10-H10
A11: Banking | B11: BNK | C11: 35 | D11: 19 | E11: 16 | F11: =COUNTIF('BNK Banking'!$I:$I,"Pass") | G11: =COUNTIF('BNK Banking'!$I:$I,"Fail") | H11: =COUNTIF('BNK Banking'!$I:$I,"Blocked") | I11: =C11-F11-G11-H11
A12: Security, Users & Auth | B12: SEC | C12: 60 | D12: 25 | E12: 35 | F12: =COUNTIF('SEC Security, Users & Auth'!$I:$I,"Pass") | G12: =COUNTIF('SEC Security, Users & Auth'!$I:$I,"Fail") | H12: =COUNTIF('SEC Security, Users & Auth'!$I:$I,"Blocked") | I12: =C12-F12-G12-H12
A13: Settings | B13: SET | C13: 35 | D13: 15 | E13: 20 | F13: =COUNTIF('SET Settings'!$I:$I,"Pass") | G13: =COUNTIF('SET Settings'!$I:$I,"Fail") | H13: =COUNTIF('SET Settings'!$I:$I,"Blocked") | I13: =C13-F13-G13-H13
A14: TOTAL | C14: =SUM(C4:C13) | D14: =SUM(D4:D13) | E14: =SUM(E4:E13) | F14: =SUM(F4:F13) | G14: =SUM(G4:G13) | H14: =SUM(H4:H13) | I14: =SUM(I4:I13)

Sheet PRD Products & Inventory
A1: ID | B1: Area | C1: Title | D1: Type | E1: Role | F1: Pre-condition | G1: Steps | H1: Expected | I1: Pass/Fail | J1: Notes
A2: PRD-01 | B2: Create Category | C2: Admin creates a category successfully | D2: Positive | E2: admin | F2: Logged in as admin/Admin@1234. No category with name 'Electronics' or prefix 'ELC' exists. | G2: 1) POST /api/v1/categories/ with body {"name":"Electronics","prefix":"elc","default_gst_percent":18}. 2) Observe response. | H2: HTTP 201. Category created; prefix stored uppercased as 'ELC' (field_validator _upper_prefix); sequence_counter=0; is_active=true.
A3: PRD-02 | B3: Create Category | C3: Duplicate category prefix rejected | D3: Negative | E3: admin | F3: Logged in as admin. A category already exists with prefix 'ELC'. | G3: 1) POST /api/v1/categories/ with {"name":"Electronics2","prefix":"ELC"}. 2) Observe response. | H3: HTTP 400, detail: "Prefix 'ELC' already exists" (CategoryService.create duplicate-prefix guard).
A4: PRD-03 | B4: Create Category | C4: Duplicate category name rejected | D4: Negative | E4: admin | F4: Logged in as admin. A category named 'Electronics' exists; prefix 'ELC2' is free. | G4: 1) POST /api/v1/categories/ with {"name":"Electronics","prefix":"ELC2"}. 2) Observe response. | H4: HTTP 400, detail: "Category name already exists" (CategoryService.create duplicate-name guard).
A5: PRD-04 | B5: Create Category | C5: Non-admin (sales) forbidden from creating category | D5: Negative | E5: sales | F5: Logged in as a user with role 'sales'. | G5: 1) POST /api/v1/categories/ with a valid body. 2) Observe response. | H5: HTTP 403, detail: "Admin access required" (route depends on require_admin).
A6: PRD-05 | B6: Create Category | C6: Unauthenticated category create rejected | D6: Negative | E6: unauthenticated | F6: No Authorization header / invalid token. | G6: 1) POST /api/v1/categories/ with a valid body and no Bearer token. 2) Observe response. | H6: HTTP 401 (get_current_user / require_admin rejects missing/invalid token).
A7: PRD-06 | B7: Delete Category | C7: Delete category that still has products is blocked | D7: Negative | E7: admin | F7: Logged in as admin. Category id=X has at least one product assigned. | G7: 1) DELETE /api/v1/categories/{X}. 2) Observe response. | H7: HTTP 400, detail: "Cannot delete category with existing products. Deactivate instead." (CategoryService.delete guard).
A8: PRD-07 | B8: Get Category | C8: Get non-existent category returns 404 | D8: Negative | E8: any-authenticated | F8: Logged in as any authenticated user. Category id 999999 does not exist. | G8: 1) GET /api/v1/categories/999999. 2) Observe response. | H8: HTTP 404, detail: "Category not found" (CategoryService.get_by_id).
A9: PRD-08 | B9: Create Product | C9: Admin creates a product with valid ordered prices | D9: Positive | E9: admin | F9: Logged in as admin. Active category id=1 (prefix 'GTY', sequence_counter=N) exists. | G9: 1) POST /api/v1/products/ with {"part_name":"Widget","category_id":1,"hsn_code":"85162000","gst_percent":18,"purchase_cost":1000,"floor_price":1200,"b2b_price":1500,"b2c_price":1650,"mrp":1800}. 2) Observe response. | H9: HTTP 201. Product created with auto part_code 'GTY{N+1}'; an initial ProductCostHistory row recorded; response includes profit_percent/profit_value and total_stock=0.
A10: PRD-09 | B10: Create Product | C10: Create product against inactive/missing category rejected | D10: Negative | E10: admin | F10: Logged in as admin. Category id=777 is inactive or does not exist. | G10: 1) POST /api/v1/products/ with category_id=777 and otherwise valid body. 2) Observe response. | H10: HTTP 404, detail: "Category not found or inactive" (ProductService.create category check on is_active==True).
A11: PRD-10 | B11: Create Product | C11: Floor price below purchase cost rejected | D11: Negative | E11: admin | F11: Logged in as admin. Active category id=1 exists. | G11: 1) POST /api/v1/products/ with purchase_cost=1000, floor_price=900, b2b_price=1500, b2c_price=1650, mrp=1800. 2) Observe response. | H11: HTTP 400, detail: "Floor price (₹900) cannot be below purchase cost (₹1000)" (price_order_error Rule 1).
A12: PRD-11 | B12: Create Product | C12: Out-of-order selling tiers rejected (B2B exceeds B2C) | D12: Negative | E12: admin | F12: Logged in as admin. Active category id=1 exists. | G12: 1) POST /api/v1/products/ with floor_price=1200, b2b_price=1700, b2c_price=1650, mrp=1800, purchase_cost=1000. 2) Observe response. | H12: HTTP 400, detail: "B2B price (₹1700) cannot exceed B2C price (₹1650)" (price_order_error Rule 2 floor<=b2b<=b2c<=mrp).
A13: PRD-12 | B13: Create Product | C13: Invalid HSN code rejected (schema) | D13: Negative | E13: admin | F13: Logged in as admin. Active category id=1 exists. | G13: 1) POST /api/v1/products/ with hsn_code="123" (3 digits) and otherwise valid body. 2) Observe response. | H13: HTTP 422, validation error: "hsn_code must be 4/6/8 digits, numeric only" (_validate_hsn in ProductCreate).
... A66: PRD-65 | B66: Price Alerts | C66: Sales role forbidden from unread price alerts | D66: Negative | E66: sales | F66: Logged in as role 'sales'. | G66: 1) GET /api/v1/price-history/alerts/unread. 2) Observe response. | H66: HTTP 403, detail: "Admin access required" (get_price_alerts depends on require_admin).

Sheet PUR Purchase
A1: ID | B1: Area | C1: Title | D1: Type | E1: Role | F1: Pre-condition | G1: Steps | H1: Expected | I1: Pass/Fail | J1: Notes
A2: PUR-01 | B2: Create Vendor | C2: Create vendor with valid GSTIN derives state_code | D2: Positive | E2: accountant | F2: Logged in as accountant (or admin/super_admin). No vendor exists with GSTIN 29ABCDE1234F1Z5. | G2: 1) POST /api/v1/vendors/ with body {trade_name:'Acme Supplies', gstin:'29ABCDE1234F1Z5', credit_days:30} 2) Note state_code in response 3) GET the created vendor. | H2: HTTP 201. Vendor created; state_code auto-derived to 29 (first two GSTIN digits). outstanding_balance = 0. GSTIN stored upper-cased.
A3: PUR-02 | B3: Create Vendor | C3: Duplicate GSTIN rejected on create | D3: Negative | E3: accountant | F3: A vendor already exists with GSTIN 29ABCDE1234F1Z5 (e.g. created by PUR-01). | G3: 1) POST /api/v1/vendors/ with body {trade_name:'Acme Two', gstin:'29ABCDE1234F1Z5'}. | H3: HTTP 400, detail = 'Vendor with this GSTIN already exists'.
A4: PUR-03 | B4: Create Vendor | C4: Malformed GSTIN rejected by schema validation | D4: Negative | E4: accountant | F4: Logged in as accountant. | G4: 1) POST /api/v1/vendors/ with body {trade_name:'Bad GST', gstin:'29ABCDE1234F1Z'} (14 chars / wrong pattern). | H4: HTTP 422. Validation error message: 'Invalid GSTIN format (expected 15 chars: 2-digit state + 10-char PAN + entity + Z + checksum)'.
A5: PUR-04 | B5: Create Vendor | C5: Missing required trade_name rejected | D5: Negative | E5: accountant | F5: Logged in as accountant. | G5: 1) POST /api/v1/vendors/ with body {gstin:'29ABCDE1234F1Z5'} (no trade_name). | H5: HTTP 422. Pydantic 'field required' error for trade_name (min_length 1).
A6: PUR-05 | B6: Create Vendor (RBAC) | C6: Sales role forbidden from creating vendor | D6: Negative | E6: sales | F6: Logged in as a user with role 'sales'. Endpoint uses require_admin_or_accountant. | G6: 1) POST /api/v1/vendors/ with a valid vendor body. | H6: HTTP 403 (admin/accountant/super_admin only). Vendor not created.
A7: PUR-06 | B7: Create Vendor (RBAC) | C7: Unauthenticated request rejected | D7: Negative | E7: unauthenticated | F7: No Authorization header / invalid token. | G7: 1) POST /api/v1/vendors/ with no Bearer token. | H7: HTTP 401 Unauthorized. No vendor created.
A8: PUR-07 | B8: Update Vendor | C8: Block deactivation when outstanding balance non-zero | D8: Negative | E8: accountant | F8: Vendor V exists and has at least one non-cancelled purchase making outstanding balance > 0 (credit ledger entries exceed debits). | G8: 1) PUT /api/v1/vendors/{V} with body {is_active:false}. | H8: HTTP 400, detail = 'Cannot deactivate vendor with non-zero outstanding balance ({amount})'. Vendor remains active.
A9: PUR-08 | B9: Update Vendor | C9: Changing GSTIN to one used by another vendor rejected | D9: Negative | E9: admin | F9: Vendor A has GSTIN 27AAAAA0000A1Z5; Vendor B exists with a different GSTIN. | G9: 1) PUT /api/v1/vendors/{B} with body {gstin:'27AAAAA0000A1Z5'}. | H9: HTTP 400, detail = 'Another vendor already uses this GSTIN'.
A10: PUR-09 | B10: Update Vendor | C10: Deactivate vendor with zero outstanding succeeds | D10: Positive | E10: admin | F10: Vendor V exists, is_active=true, and has zero outstanding balance (no purchases or all settled/cancelled). | G10: 1) PUT /api/v1/vendors/{V} with body {is_active:false} 2) GET the vendor. | H10: HTTP 200. Vendor is_active=false.
A11: PUR-10 | B11: Get Vendor | C11: Get non-existent vendor returns 404 | D11: Negative | E11: accountant | F11: No vendor with id 999999. | G11: 1) GET /api/v1/vendors/999999. | H11: HTTP 404, detail = 'Vendor not found'.
A12: PUR-11 | B12: Vendor Ledger (RBAC) | C12: Vendor ledger restricted to admin/accountant | D12: Negative | E12: sales | F12: Logged in as sales; vendor V exists. Endpoint uses require_admin_or_accountant. | G12: 1) GET /api/v1/vendors/{V}/ledger. | H12: HTTP 403. Ledger not returned.
A13: PUR-12 | B13: Create Purchase | C13: Happy-path purchase creation with stock, journal, ledger | D13: Positive | E13: accountant | F13: Active vendor V, active warehouse W, active product P (with gst_percent, hsn) all exist. No non-cancelled purchase for V with invoice number INV-100. | G13: 1) POST /api/v1/purchases/ with {vendor_id:V, warehouse_id:W, vendor_invoice_number:'INV-100', invoice_date:'2026-05-10', items:[{product_id:P, quantity:10, unit_cost:50, gst_percent:18, hsn_code:'8471'}]} 2) GET the returned purchase 3) Check vendor ledger. | H13: HTTP 201. purchase_number auto-generated PO-2026-2027-NNNN. subtotal=500, GST computed (CGST+SGST or IGST per state), total_amount=590. Stock layer added (FIFO), vendor ledger credit posted, journal STOCK debit + CREDITORS credit + GST_ITC debit balanced.
... A53: PUR-52 | B53: GSTIN Lookup | C53: GSTIN lookup returns structured error (not exception) on upstream failure | D53: Positive | E53: any-authenticated | F53: Logged in; Cleartax sandbox/token configured. Endpoint uses get_current_user. | G53: 1) GET /api/v1/vendors/gstin-lookup/29ABCDE1234F1Z5. | H53: HTTP 200. On success returns trade_name/legal_name/state/etc.; on upstream 401/403 returns {error, error_code:'unauthorized'}; on 404 {error_code:'not_found'}; on timeout {error_code:'timeout'} — endpoint never 500s for these.

Sheet BIL Billing & Sales
A1: ID | B1: Area | C1: Title | D1: Type | E1: Role | F1: Pre-condition | G1: Steps | H1: Expected | I1: Pass/Fail | J1: Notes
A2: BIL-01 | B2: Create Customer | C2: Create B2B customer with valid GSTIN | D2: Positive | E2: any-authenticated | F2: Logged in with a valid token (e.g. admin/Admin@1234). No existing customer uses GSTIN 29ABCDE1234F1Z5. | G2: 1) POST /api/v1/customers/ with body {trade_name:'Acme Traders', gstin:'29ABCDE1234F1Z5', state:'Karnataka', state_code:29, credit_limit:100000}. 2) Note returned id. | H2: HTTP 201. Response JSON has id, trade_name='Acme Traders', gstin, outstanding_balance=0, addresses=[].
A3: BIL-02 | B3: Create Customer | C3: Duplicate GSTIN rejected | D3: Negative | E3: any-authenticated | F3: A customer already exists with GSTIN 29ABCDE1234F1Z5 (from BIL-01). | G3: 1) POST /api/v1/customers/ with body {trade_name:'Acme Dup', gstin:'29ABCDE1234F1Z5'}. | H3: HTTP 400, detail = 'Customer with this GSTIN already exists'.
A4: BIL-03 | B4: Create Customer | C4: Missing trade_name rejected | D4: Negative | E4: any-authenticated | F4: Logged in with valid token. | G4: 1) POST /api/v1/customers/ with body {gstin:'29ZZZZZ1234F1Z5'} (no trade_name). | H4: HTTP 422 (Pydantic validation; trade_name is required, min_length 1).
A5: BIL-04 | B5: Create Customer | C5: Unauthenticated create blocked | D5: Negative | E5: unauthenticated | F5: No Authorization header / invalid token. | G5: 1) POST /api/v1/customers/ with no token and body {trade_name:'NoAuth'}. | H5: HTTP 401, detail = 'Could not validate credentials' (get_current_user).
A6: BIL-05 | B6: Update Customer | C6: Admin updates credit_limit | D6: Positive | E6: admin | F6: Customer id=1 exists. Logged in as admin or super_admin. | G6: 1) PUT /api/v1/customers/1 with body {credit_limit:250000}. | H6: HTTP 200. Customer returned with credit_limit=250000.
A7: BIL-06 | B7: Update Customer | C7: Sales/accountant blocked from changing credit_limit | D7: Negative | E7: sales | F7: Customer id=1 exists. Logged in as a non-admin role (sales or accountant). | G7: 1) PUT /api/v1/customers/1 with body {credit_limit:999999}. | H7: HTTP 403, detail = 'Only admins may modify: credit_limit' (endpoint admin_only_fields guard).
A8: BIL-07 | B8: Update Customer | C8: Sales blocked from multiple admin-only fields (sorted message) | D8: Negative | E8: sales | F8: Customer id=1 exists. Logged in as sales. | G8: 1) PUT /api/v1/customers/1 with body {credit_days:60, gst_status:'Active', is_active:false}. | H8: HTTP 403, detail = 'Only admins may modify: credit_days, gst_status, is_active' (alphabetically sorted).
A9: BIL-08 | B9: Update Customer | C9: Sales may update non-sensitive fields | D9: Positive | E9: sales | F9: Customer id=1 exists. Logged in as sales. | G9: 1) PUT /api/v1/customers/1 with body {phone:'9876543210', contact_person:'Ravi'}. | H9: HTTP 200. Customer updated; no 403 since none of credit_limit/credit_days/gst_status/is_active sent.
A10: BIL-09 | B10: Update Customer | C10: Update non-existent customer | D10: Negative | E10: admin | F10: No customer with id=999999. Logged in as admin. | G10: 1) PUT /api/v1/customers/999999 with body {phone:'12345'}. | H10: HTTP 404, detail = 'Customer not found'.
A11: BIL-10 | B11: Customer Ledger | C11: Accountant views customer ledger | D11: Positive | E11: accountant | F11: Customer id=1 exists with ledger entries. Logged in as accountant. | G11: 1) GET /api/v1/customers/1/ledger?page=1&page_size=50. | H11: HTTP 200. Body has items, customer_name, outstanding_balance, credit_limit, credit_days.
A12: BIL-11 | B12: Customer Ledger | C12: Sales role forbidden from ledger | D12: Negative | E12: sales | F12: Customer id=1 exists. Logged in as sales. | G12: 1) GET /api/v1/customers/1/ledger. | H12: HTTP 403, detail = 'Admin or Accountant access required' (require_admin_or_accountant).
A13: BIL-12 | B13: Customer Statement | C13: Statement requires date_from and date_to | D13: Negative | E13: accountant | F13: Customer id=1 exists. Logged in as accountant. | G13: 1) GET /api/v1/customers/1/statement with no date_from/date_to query params. | H13: HTTP 422 (date_from and date_to are required Query(...) params).
... A57: BIL-56 | B57: Add Customer Address | C57: Add address to non-existent customer | D57: Negative | E57: any-authenticated | F57: No customer id=999999. Logged in. | G57: 1) POST /api/v1/customers/999999/addresses body {label:'Office', address_line1:'1 MG Rd', city:'Bengaluru', state:'Karnataka', pincode:'560001'}. | H57: HTTP 404, detail = 'Customer not found'.

Sheet WH Warehouse
A1: ID | B1: Area | C1: Title | D1: Type | E1: Role | F1: Pre-condition | G1: Steps | H1: Expected | I1: Pass/Fail | J1: Notes
A2: WH-01 | B2: Create Warehouse | C2: Admin creates a warehouse with unique code | D2: Positive | E2: admin | F2: Authenticated as admin; no warehouse with code 'WH-A' exists | G2: 1) POST /api/v1/warehouses/ with body {name:'Main Depot', code:'WH-A', city:'Chennai', state:'Tamil Nadu', is_default:false} 2) Inspect response | H2: HTTP 201; JSON returns the created warehouse {id, name:'Main Depot', code:'WH-A', is_active:true}
A3: WH-02 | B3: Create Warehouse | C3: Creating warehouse with duplicate code is rejected | D3: Negative | E3: admin | F3: A warehouse with code 'WH-A' already exists (WH-01) | G3: 1) POST /api/v1/warehouses/ with body {name:'Other', code:'WH-A'} 2) Inspect response | H3: HTTP 400; detail = 'Warehouse code already exists'
A4: WH-03 | B4: Create Warehouse | C4: Setting is_default true unsets default on all others | D4: Positive | E4: admin | F4: An existing warehouse currently has is_default=true | G4: 1) POST /api/v1/warehouses/ with {name:'New Default', code:'WH-DEF', is_default:true} 2) GET /api/v1/warehouses/ and check is_default flags | H4: HTTP 201; new warehouse is_default=true; previously-default warehouse now is_default=false
A5: WH-04 | B5: Create Warehouse | C5: Missing required field (code) returns validation error | D5: Negative | E5: admin | F5: Authenticated as admin | G5: 1) POST /api/v1/warehouses/ with body {name:'NoCode'} (omit code) 2) Inspect response | H5: HTTP 422; validation error citing missing 'code' field
A6: WH-05 | B6: Create Warehouse | C6: Non-admin (sales) cannot create a warehouse | D6: Negative | E6: sales | F6: Authenticated as a sales user | G6: 1) POST /api/v1/warehouses/ with {name:'X', code:'WH-X'} 2) Inspect response | H6: HTTP 403; detail = 'Admin access required' (require_admin)
A7: WH-06 | B7: Create Warehouse | C7: Unauthenticated request to create warehouse is rejected | D7: Negative | E7: unauthenticated | F7: No Authorization header / invalid token | G7: 1) POST /api/v1/warehouses/ with {name:'X', code:'WH-Y'} and no Bearer token 2) Inspect response | H7: HTTP 401 (not authenticated)
A8: WH-07 | B8: List Warehouses | C8: Any authenticated user lists active warehouses with stock value | D8: Positive | E8: any-authenticated | F8: At least one active warehouse exists with FIFO stock entries | G8: 1) GET /api/v1/warehouses/ as accountant 2) Inspect response | H8: HTTP 200; array of active warehouses each with a 'stock_value' computed from StockEntry remaining_qty*unit_cost; default warehouse sorted first
A9: WH-08 | B9: List Warehouses | C9: include_inactive returns obsoleted warehouses too | D9: Positive | E9: any-authenticated | F9: At least one warehouse with is_active=false exists | G9: 1) GET /api/v1/warehouses/?include_inactive=true 2) Compare with GET /api/v1/warehouses/ (default) | H9: HTTP 200; include_inactive=true list contains the inactive warehouse; default list excludes it
A10: WH-09 | B10: Get Warehouse | C10: Get non-existent warehouse returns 404 | D10: Negative | E10: any-authenticated | F10: No warehouse with id 999999 | G10: 1) GET /api/v1/warehouses/999999 2) Inspect response | H10: HTTP 404; detail = 'Warehouse not found'
A11: WH-10 | B11: Update Warehouse | C11: Admin updates warehouse fields (exclude_none) | D11: Positive | E11: admin | F11: Warehouse id=1 exists | G11: 1) PUT /api/v1/warehouses/1 with {city:'Mumbai', contact_person:'Ravi'} 2) GET /api/v1/warehouses/1 | H11: HTTP 200; city and contact_person updated; fields left as null in payload unchanged (exclude_none)
A12: WH-11 | B12: Update Warehouse | C12: Update non-existent warehouse returns 404 | D12: Negative | E12: admin | F12: No warehouse id 999999 | G12: 1) PUT /api/v1/warehouses/999999 with {city:'X'} 2) Inspect response | H12: HTTP 404; detail = 'Warehouse not found'
A13: WH-12 | B13: Update Warehouse | C13: Non-admin cannot update a warehouse | D13: Negative | E13: sales | F13: Warehouse id=1 exists; logged in as sales | G13: 1) PUT /api/v1/warehouses/1 with {city:'X'} 2) Inspect response | H13: HTTP 403; detail = 'Admin access required' (require_admin)
... A65: WH-64 | B65: Rename Warehouse | C65: Super-admin renames any warehouse (code not editable) | D65: Positive | E65: super_admin | F65: Warehouse id=5 exists with code 'WH-5' | G65: 1) PUT /api/v1/warehouses/5/rename with {name:'Renamed Depot', code:'HACK', city:'Pune'} 2) GET /api/v1/warehouses/5 | H65: HTTP 200; name updated to 'Renamed Depot' and city to 'Pune'; code remains 'WH-5' (code is not in allowed rename fields)

Sheet ACC Accounting
A1: ID | B1: Area | C1: Title | D1: Type | E1: Role | F1: Pre-condition | G1: Steps | H1: Expected | I1: Pass/Fail | J1: Notes
A2: ACC-01 | B2: Create Cheque | C2: Create cheque with valid data succeeds | D2: Positive | E2: accountant | F2: An existing active customer (customer_id) exists. Logged in as accountant with valid token. | G2: 1) POST /api/v1/cheques/ with body {cheque_number:'CHQ1001', cheque_date:'2026-05-20', bank_name:'HDFC Bank', amount:5000.00, customer_id:<id>, is_pdc:false} 2) Inspect response | H2: HTTP 201. Response JSON has id, cheque_number='CHQ1001', amount=5000.00, status='received', customer_name set, is_pdc=false.
A3: ACC-02 | B3: Create Cheque | C3: Create PDC cheque sets is_pdc true and status received | D3: Positive | E3: admin | F3: Logged in as admin. | G3: 1) POST /api/v1/cheques/ with {cheque_number:'CHQ1002', cheque_date:'2026-06-15', bank_name:'ICICI', amount:1200.50, is_pdc:true} | H3: HTTP 201. Response status='received', is_pdc=true, amount=1200.50.
A4: ACC-03 | B4: Create Cheque | C4: Create cheque with zero/negative amount rejected | D4: Negative | E4: accountant | F4: Logged in as accountant. | G4: 1) POST /api/v1/cheques/ with {cheque_number:'CHQ0', cheque_date:'2026-05-20', bank_name:'SBI', amount:0} | H4: HTTP 422 Unprocessable Entity. Validation error on 'amount' (Field gt=0 constraint).
A5: ACC-04 | B5: Create Cheque | C5: Create cheque with empty cheque_number rejected | D5: Negative | E5: accountant | F5: Logged in as accountant. | G5: 1) POST /api/v1/cheques/ with {cheque_number:'', cheque_date:'2026-05-20', bank_name:'SBI', amount:100} | H5: HTTP 422. Validation error on 'cheque_number' (min_length=1).
A6: ACC-05 | B6: Create Cheque | C6: Unauthenticated cheque create blocked | D6: Negative | E6: unauthenticated | F6: No Authorization header / invalid token. | G6: 1) POST /api/v1/cheques/ with valid body and NO bearer token | H6: HTTP 401 Unauthorized, detail 'Could not validate credentials'.
A7: ACC-06 | B7: Create Cheque | C7: Sales role forbidden from cheque create | D7: Negative | E7: sales | F7: Logged in as a user with role 'sales'. | G7: 1) POST /api/v1/cheques/ with valid body | H7: HTTP 403 Forbidden, detail 'Admin or Accountant access required' (require_admin_or_accountant).
A8: ACC-07 | B8: Deposit Cheque | C8: Deposit a received cheque succeeds | D8: Positive | E8: accountant | F8: A cheque in status 'received' exists (cheque_id). | G8: 1) POST /api/v1/cheques/{cheque_id}/deposit with {deposit_date:'2026-05-25'} | H8: HTTP 200. Response status='deposited', deposit_date='2026-05-25'.
A9: ACC-08 | B9: Deposit Cheque | C9: Deposit a cleared cheque blocked by status guard | D9: Negative | E9: accountant | F9: A cheque already in status 'cleared' exists (cheque_id). | G9: 1) POST /api/v1/cheques/{cheque_id}/deposit with {deposit_date:'2026-05-25'} | H9: HTTP 400, detail 'Cannot deposit cheque in status: ChequeStatus.cleared' (status not in received/pdc_pending).
A10: ACC-09 | B10: Deposit Cheque | C10: Deposit non-existent cheque returns 404 | D10: Negative | E10: accountant | F10: No cheque with id 999999 exists. | G10: 1) POST /api/v1/cheques/999999/deposit with {deposit_date:'2026-05-25'} | H10: HTTP 404, detail 'Cheque not found'.
A11: ACC-10 | B11: Clear Cheque | C11: Clear a deposited cheque succeeds | D11: Positive | E11: admin | F11: A cheque in status 'deposited' exists (cheque_id). | G11: 1) POST /api/v1/cheques/{cheque_id}/clear with {clearance_date:'2026-05-28'} | H11: HTTP 200. Response status='cleared', clearance_date='2026-05-28'.
A12: ACC-11 | B12: Clear Cheque | C12: Clear a received (not deposited) cheque blocked | D12: Negative | E12: accountant | F12: A cheque in status 'received' exists (cheque_id). | G12: 1) POST /api/v1/cheques/{cheque_id}/clear with {clearance_date:'2026-05-28'} | H12: HTTP 400, detail 'Cheque must be deposited before clearing'.
A13: ACC-12 | B13: Bounce Cheque | C13: Bounce cheque records bounce details and reverses linked receipt | D13: Positive | E13: accountant | F13: A cheque exists with customer_id and receipt_id linked to a CustomerPayment, and at least one prior LedgerEntry for that customer. | G13: 1) POST /api/v1/cheques/{cheque_id}/bounce with {bounce_date:'2026-05-30', bounce_reason:'Insufficient funds', bounce_charges:250.00} 2) Check customer ledger | H13: HTTP 200. status='bounced', bounce_reason set, bounce_charges=250.00. A new debit LedgerEntry of cheque amount with reference_type='cheque_bounce' appended increasing customer balance.
... A39: ACC-38 | B39: Role Access | C39: super_admin can access admin-only expense approval | D39: Positive | E39: super_admin | F39: An expense in status 'pending_approval' exists. Logged in as super_admin. | G39: 1) POST /api/v1/expenses/{expense_id}/approve with {approved:true} | H39: HTTP 200. Approval succeeds (super_admin satisfies require_admin).

Sheet GST GST E-Invoice E-Way Bill
A1: ID | B1: Area | C1: Title | D1: Type | E1: Role | F1: Pre-condition | G1: Steps | H1: Expected | I1: Pass/Fail | J1: Notes
A2: GST-01 | B2: List Transporters | C2: Authenticated user lists active transporters | D2: Positive | E2: any-authenticated | F2: At least one Transporter row with is_active=true exists. Valid token for any role (e.g. sales). | G2: 1) GET /api/v1/transporters/ with a valid Bearer token (any role). 2) Inspect response. | H2: HTTP 200. JSON array of active transporters sorted by name, each with id, name, gstin, contact_person, phone, email, is_active, created_at. Inactive transporters (is_active=false) are excluded.
A3: GST-02 | B3: List Transporters | C3: Unauthenticated transporter list is rejected | D3: Negative | E3: unauthenticated | F3: No Authorization header. | G3: 1) GET /api/v1/transporters/ with no token. | H3: HTTP 401 with detail 'Could not validate credentials' (get_current_user dependency).
A4: GST-03 | B4: Create Transporter | C4: Accountant creates a transporter | D4: Positive | E4: accountant | F4: Valid accountant token. | G4: 1) POST /api/v1/transporters/ body {"name":"Blue Dart Logistics","gstin":"29ABCDE1234F1Z5","contact_person":"Ravi","phone":"9999999999","email":"ops@bluedart.in"}. | H4: HTTP 201. Returns created transporter with new id, is_active true, created_at populated; created_by set to the accountant's user id.
A5: GST-04 | B5: Create Transporter | C5: Sales role forbidden from creating transporter | D5: Negative | E5: sales | F5: Valid sales token. | G5: 1) POST /api/v1/transporters/ with a valid name payload using a sales token. | H5: HTTP 403 with detail 'Admin or Accountant access required' (require_admin_or_accountant).
A6: GST-05 | B6: Create Transporter | C6: Missing name fails validation | D6: Negative | E6: admin | F6: Valid admin token. | G6: 1) POST /api/v1/transporters/ body {"gstin":"29ABCDE1234F1Z5"} (no name). 2) Also try name:"" (empty). | H6: HTTP 422 Unprocessable Entity (name is required, min_length=1) from Pydantic TransporterCreate.
A7: GST-06 | B7: Create Vehicle | C7: Admin creates a vehicle linked to a transporter | D7: Positive | E7: admin | F7: Valid admin token; an existing transporter id (e.g. 1). | G7: 1) POST /api/v1/vehicles/ body {"vehicle_number":"KA01AB1234","vehicle_type":"Truck","owner_name":"Self","transporter_id":1}. | H7: HTTP 201. Returns vehicle with id, vehicle_number, vehicle_type, owner_name, transporter_id=1, transporter_name resolved to that transporter's name, is_active true.
A8: GST-07 | B8: List Vehicles | C8: Filter vehicles by transporter_id | D8: Positive | E8: any-authenticated | F8: Vehicles exist for transporter 1 and transporter 2. | G8: 1) GET /api/v1/vehicles/?transporter_id=1 with any valid token. | H8: HTTP 200. Array contains only active vehicles whose transporter_id=1, sorted by vehicle_number, each with transporter_name populated.
A9: GST-08 | B9: Create Vehicle | C9: Missing vehicle_number / vehicle_type fails | D9: Negative | E9: accountant | F9: Valid accountant token. | G9: 1) POST /api/v1/vehicles/ body {"owner_name":"X"} (no vehicle_number, no vehicle_type). | H9: HTTP 422 (vehicle_number and vehicle_type both required, min_length=1).
A10: GST-09 | B10: Generate E-Invoice | C10: Generate IRN for a valid B2B invoice (sandbox mock) | D10: Positive | E10: accountant | F10: CLEARTAX_SANDBOX=true and CLEARTAX_AUTH_TOKEN empty (mock mode). A B2B invoice (document_type=b2b_invoice) that is not cancelled, has no IRN, valid invoice number, valid line items (numeric HSN >= 6 digits, valid GST rate, qty>0), reconciling totals, and a customer with valid/empty GSTIN. | G10: 1) POST /api/v1/einvoice/generate body {"invoice_id":<id>}. | H10: HTTP 200. Response has irn like 'MOCK-IRN-<invoice_number>-<id>', irn_status 'generated', qr_code 'MOCK-QR-<id>', ack_number 'MOCK-ACK-<id>', error_message null. Invoice row updated with irn, irn_generated_at; an EInvoiceLog with status generated is created.
A11: GST-10 | B11: Generate E-Invoice | C11: Generate IRN for non-existent invoice | D11: Negative | E11: admin | F11: No invoice with id 999999. | G11: 1) POST /api/v1/einvoice/generate body {"invoice_id":999999}. | H11: HTTP 404 with detail 'Invoice not found'.
A12: GST-11 | B12: Generate E-Invoice | C12: Generate IRN for a cancelled invoice is blocked | D12: Negative | E12: admin | F12: An invoice with is_cancelled=true. | G12: 1) POST /api/v1/einvoice/generate with that invoice_id. | H12: HTTP 400 with detail 'Cannot generate IRN for cancelled invoice'.
A13: GST-12 | B13: Generate E-Invoice | C13: Re-generating IRN when one already exists is blocked | D13: Negative | E13: accountant | F13: An invoice that already has irn set (e.g. from GST-09). | G13: 1) POST /api/v1/einvoice/generate with that invoice_id again. | H13: HTTP 400 with detail 'IRN already generated: <existing_irn>'.
... A47: GST-46 | B47: GSTR-3B | C47: Unauthenticated GSTR-3B request rejected | D47: Negative | E47: unauthenticated | F47: No token. | G47: 1) GET /api/v1/gstr3b/?period=01-2026&financial_year=2025-26 with no Authorization header. | H47: HTTP 401 'Could not validate credentials'.

Sheet RPT Reports & Dashboard
A1: ID | B1: Area | C1: Title | D1: Type | E1: Role | F1: Pre-condition | G1: Steps | H1: Expected | I1: Pass/Fail | J1: Notes
A2: RPT-01 | B2: Dashboard | C2: Get dashboard metrics for current FY (default) | D2: Positive | E2: any-authenticated | F2: At least one non-cancelled b2b/b2c invoice, one purchase, stock entries and an approved cash closing exist for the current FY. | G2: 1) Authenticate as any valid user (e.g. accountant). 2) GET /api/v1/dashboard/ with no query params. | H2: 200 OK. JSON contains keys: today_sales, today_sales_net, month_sales, fy_sales, total_outstanding, overdue_amount, total_payables, month_purchases, fy_purchases, stock_value, pending_deliveries, low_stock_count, cash_balance, today_collections, top_customers (<=5), recent_invoices (<=5), monthly_trend (6 entries), financial_year (= current FY), as_of (today IST).
A3: RPT-02 | B3: Dashboard | C3: Get dashboard metrics for explicit financial_year | D3: Positive | E3: any-authenticated | F3: Sales/purchase data exists for FY 2024. | G3: 1) Authenticate as sales user. 2) GET /api/v1/dashboard/?financial_year=2024. | H3: 200 OK. fy_start computed as 2024-04-01, fy_end 2025-04-01; fy_sales/fy_purchases reflect that window; response.financial_year == "2024".
A4: RPT-03 | B4: Dashboard | C4: Dashboard degrades gracefully when one metric query fails | D4: Positive | E4: any-authenticated | F4: DB reachable; ability to make one underlying metric error (e.g. a corrupt/missing optional column the auto-migrate did not add). | G4: 1) Authenticate. 2) GET /api/v1/dashboard/. | H4: 200 OK (no 500). The failing metric returns its safe default (0.0, 0.0, [] or 0) per _safe() while all other metrics populate normally; warning logged server-side.
A5: RPT-04 | B5: Dashboard | C5: Dashboard unauthenticated request rejected | D5: Negative | E5: unauthenticated | F5: No Authorization header. | G5: 1) GET /api/v1/dashboard/ with no token. | H5: 401 Unauthorized (Not authenticated).
A6: RPT-05 | B6: Dashboard | C6: Dashboard with invalid/expired token rejected | D6: Negative | E6: unauthenticated | F6: Have a malformed or expired bearer token. | G6: 1) GET /api/v1/dashboard/ with Authorization: Bearer badtoken. | H6: 401 Unauthorized (Could not validate credentials).
A7: RPT-06 | B7: Sales Report | C7: Generate sales report for date range | D7: Positive | E7: any-authenticated | F7: Non-cancelled b2b/b2c invoices exist between the dates. | G7: 1) Authenticate as sales user. 2) GET /api/v1/reports/sales?date_from=2025-04-01&date_to=2025-05-31. | H7: 200 OK. rows[] (default only b2b_invoice/b2c_invoice, is_cancelled=False), invoice_count matches rows length, ordered by invoice_date desc; summary has total_taxable, total_tax, total_amount, total_outstanding, total_collected (=total_amount-total_outstanding).
A8: RPT-07 | B8: Sales Report | C8: Sales report filtered by customer, product, document_type and FY | D8: Positive | E8: any-authenticated | F8: Invoices exist for the given customer_id and FY. | G8: 1) Authenticate. 2) GET /api/v1/reports/sales?date_from=2025-04-01&date_to=2025-04-30&customer_id=5&document_type=b2b_invoice&financial_year=2025. | H8: 200 OK. Only invoices for customer 5, document_type b2b_invoice, financial_year 2025 in range are returned; summary recomputed for that subset.
A9: RPT-08 | B9: Sales Report | C9: Sales report cancelled invoices excluded | D9: Positive | E9: any-authenticated | F9: A cancelled invoice and a live invoice exist in the range. | G9: 1) Authenticate. 2) GET /api/v1/reports/sales?date_from=2025-04-01&date_to=2025-04-30. | H9: 200 OK. The cancelled invoice (is_cancelled=True) does NOT appear in rows and is not summed into the summary totals.
A10: RPT-09 | B10: Sales Report | C10: Sales report missing required date_from | D10: Negative | E10: any-authenticated | F10: Valid token. | G10: 1) Authenticate. 2) GET /api/v1/reports/sales?date_to=2025-04-30 (no date_from). | H10: 422 Unprocessable Entity — validation error: field 'date_from' required (query param).
A11: RPT-10 | B11: Sales Report | C11: Sales report invalid date format | D11: Negative | E11: any-authenticated | F11: Valid token. | G11: 1) Authenticate. 2) GET /api/v1/reports/sales?date_from=31-05-2025&date_to=2025-05-31. | H11: 422 Unprocessable Entity — date_from not a valid ISO date (expects YYYY-MM-DD).
A12: RPT-11 | B12: Sales Report | C12: Sales report unauthenticated | D12: Negative | E12: unauthenticated | F12: No token. | G12: 1) GET /api/v1/reports/sales?date_from=2025-04-01&date_to=2025-04-30 with no token. | H12: 401 Unauthorized (Not authenticated).
A13: RPT-12 | B13: Purchase Report | C13: Generate purchase report as accountant | D13: Positive | E13: accountant | F13: Non-cancelled purchases exist in range. | G13: 1) Authenticate as accountant. 2) GET /api/v1/reports/purchases?date_from=2025-04-01&date_to=2025-05-31. | H13: 200 OK. rows[] with vendor_invoice_number, vendor_name, subtotal, total_cgst/sgst/igst, gst_type; purchase_count matches; summary.total_taxable/total_tax/total_amount computed; cancelled purchases excluded; ordered invoice_date desc.
... A40: RPT-38 | B40: P&L Report | C40: P&L as super_admin allowed | D40: Positive | E40: super_admin | F40: super_admin token; data for FY 2025. | G40: 1) Authenticate as super_admin. 2) GET /api/v1/reports/pnl?financial_year=2025. | H40: 200 OK — super_admin satisfies require_admin_or_accountant; full P&L returned.

Sheet BNK Banking
A1: ID | B1: Area | C1: Title | D1: Type | E1: Role | F1: Pre-condition | G1: Steps | H1: Expected | I1: Pass/Fail | J1: Notes
A2: BNK-01 | B2: Generate Bank Stock Statement | C2: Generate stock statement with defaults (happy path) | D2: Positive | E2: admin | F2: Logged in as admin. At least one active product/warehouse with StockEntry remaining_qty>0 and one non-cancelled b2b/b2c invoice with outstanding_amount>0 dated on/before statement_date. | G2: 1) POST /api/v1/bank-stock-statement/ with body {statement_date:'2026-05-31', bank_name:'HDFC Bank', account_number:'1234567890'} (margin_percent omitted). 2) Inspect response. | H2: HTTP 201. Response includes auto statement_number formatted BSS-<FYwithoutdash>-0001 (e.g. BSS-20262027-0001), stock_value and debtors_value computed, margin_percent=25, drawing_power = total_value*(1-0.25) rounded to 2dp, is_locked=true, declaration text present, stock_breakup and debtor_breakup arrays populated.
A3: BNK-02 | B3: Generate Bank Stock Statement | C3: Generate with explicit margin_percent and cc_limit | D3: Positive | E3: accountant | F3: Logged in as accountant. Stock and debtor data exist. | G3: 1) POST /api/v1/bank-stock-statement/ {statement_date:'2026-05-31', bank_name:'SBI', account_number:'00112233', margin_percent:30, cc_limit:5000000, notes:'May stmt'}. 2) Inspect response. | H3: HTTP 201. margin_percent=30, drawing_power = total_value*(1-0.30) to 2dp, cc_limit=5000000.00, notes='May stmt', is_locked=true.
A4: BNK-03 | B4: Generate Bank Stock Statement | C4: Statement number increments by total existing count | D4: Positive | E4: admin | F4: Exactly N BankStockStatement rows already exist (note N). | G4: 1) POST /api/v1/bank-stock-statement/ with valid body. 2) Read statement_number suffix. | H4: HTTP 201. statement_number suffix = (N+1) zero-padded to 4 digits (e.g. if N=3 then -0004). Note: counter is global count, not per-FY.
A5: BNK-04 | B5: Generate Bank Stock Statement | C5: Drawing power excludes inactive products and inactive warehouses | D5: Positive | E5: accountant | F5: One product OR its warehouse is_active=False but has StockEntry remaining_qty>0. | G5: 1) POST /api/v1/bank-stock-statement/ valid body. 2) Inspect stock_breakup and stock_value. | H5: HTTP 201. Stock from inactive product/warehouse is NOT included in stock_value or stock_breakup (filter Product.is_active==True and Warehouse.is_active==True).
A6: BNK-05 | B6: Generate Bank Stock Statement | C6: Debtors only include non-cancelled b2b/b2c invoices with outstanding>0 | D6: Positive | E6: admin | F6: Have a cancelled invoice, a fully-paid invoice (outstanding=0), a credit note, and a valid outstanding b2b invoice all dated on/before statement_date. | G6: 1) POST valid body. 2) Inspect debtors_value and debtor_breakup. | H6: HTTP 201. Only the outstanding non-cancelled b2b/b2c invoice contributes; cancelled, fully-paid, and non-invoice document types excluded.
A7: BNK-06 | B7: Generate Bank Stock Statement | C7: As-of date filters out stock/invoices after statement_date | D7: Positive | E7: accountant | F7: A StockEntry with entry_date AFTER statement_date and an invoice with invoice_date AFTER statement_date exist. | G7: 1) POST with statement_date earlier than those rows. 2) Inspect values. | H7: HTTP 201. Entries/invoices dated after statement_date are excluded (entry_date<=as_of and invoice_date<=as_of).
A8: BNK-07 | B8: Generate Bank Stock Statement | C8: margin_percent above 100 rejected | D8: Negative | E8: admin | F8: Logged in as admin. | G8: 1) POST /api/v1/bank-stock-statement/ {statement_date:'2026-05-31', bank_name:'X', account_number:'1', margin_percent:150}. | H8: HTTP 422 validation error on margin_percent (Field le=100). No statement created.
A9: BNK-08 | B9: Generate Bank Stock Statement | C9: Negative margin_percent rejected | D9: Negative | E9: admin | F9: Logged in as admin. | G9: 1) POST with margin_percent:-5 and otherwise valid body. | H9: HTTP 422 validation error on margin_percent (Field ge=0).
A10: BNK-09 | B10: Generate Bank Stock Statement | C10: Empty bank_name rejected | D10: Negative | E10: admin | F10: Logged in as admin. | G10: 1) POST {statement_date:'2026-05-31', bank_name:'', account_number:'123'}. | H10: HTTP 422 (bank_name min_length=1).
A11: BNK-10 | B11: Generate Bank Stock Statement | C11: bank_name exceeding 100 chars rejected | D11: Negative | E11: admin | F11: Logged in as admin. | G11: 1) POST with bank_name of 101 characters, valid rest. | H11: HTTP 422 (bank_name max_length=100).
A12: BNK-11 | B12: Generate Bank Stock Statement | C12: account_number exceeding 50 chars rejected | D12: Negative | E12: admin | F12: Logged in as admin. | G12: 1) POST with account_number of 51 characters, valid rest. | H12: HTTP 422 (account_number max_length=50).
A13: BNK-12 | B13: Generate Bank Stock Statement | C13: Missing required statement_date rejected | D13: Negative | E13: admin | F13: Logged in as admin. | G13: 1) POST omitting statement_date with bank_name and account_number set. | H13: HTTP 422 (statement_date required).
... A36: BNK-35 | B36: Role-Based Access | C36: Admin allowed on notification/scheduled/backup admin-only routes | D36: Positive | E36: admin | F36: Logged in as admin. | G36: 1) GET /notifications/settings. 2) PUT /scheduled-reports/settings valid body. 3) GET /backup/status. | H36: HTTP 200 for all (require_admin permits admin).

Sheet SEC Security, Users & Auth
A1: ID | B1: Area | C1: Title | D1: Type | E1: Role | F1: Pre-condition | G1: Steps | H1: Expected | I1: Pass/Fail | J1: Notes
A2: SEC-01 | B2: Login | C2: Successful login with valid credentials returns tokens and user | D2: Positive | E2: unauthenticated | F2: Active user admin/Admin@1234 exists (seeded). | G2: 1) POST /api/v1/auth/login with {"username":"admin","password":"Admin@1234"}. | H2: 200 OK. Body contains access_token, refresh_token, token_type="bearer", and user object with id, username, full_name, email, role, page_permissions, warehouse_id. An ActiveSession and LoginHistory row are created.
A3: SEC-02 | B3: Login | C3: Login with wrong password is rejected and increments failed count | D3: Negative | E3: unauthenticated | F3: Active user exists; failed_login_count below MAX_LOGIN_ATTEMPTS. | G3: 1) POST /api/v1/auth/login with correct username and an incorrect password. | H3: 401 Unauthorized, detail="Invalid username or password". User.failed_login_count increments by 1.
A4: SEC-03 | B4: Login | C4: Login with unknown username is rejected | D4: Negative | E4: unauthenticated | F4: No user named nosuchuser. | G4: 1) POST /api/v1/auth/login with {"username":"nosuchuser","password":"x12345678"}. | H4: 401 Unauthorized, detail="Invalid username or password" (same message as wrong password — no user enumeration).
A5: SEC-04 | B5: Login | C5: Inactive/suspended user cannot log in | D5: Negative | E5: unauthenticated | F5: A user exists with is_active=false (suspended). | G5: 1) POST /api/v1/auth/login with that user's correct username/password. | H5: 401 Unauthorized, detail="Invalid username or password" (query filters is_active==True so the user is not found).
A6: SEC-05 | B6: Login | C6: Account locks after MAX_LOGIN_ATTEMPTS failures | D6: Negative | E6: unauthenticated | F6: Active user; settings.MAX_LOGIN_ATTEMPTS (default 5) and ACCOUNT_LOCKOUT_MINUTES known; failed_login_count reset to 0. | G6: 1) POST /api/v1/auth/login with wrong password repeatedly until failed_login_count reaches MAX_LOGIN_ATTEMPTS. 2) Attempt one more login (even with correct password). | H6: On the threshold attempt is_locked becomes true and locked_until is set. Subsequent login returns 401 with detail "Account locked. Try again in N minute(s)."
A7: SEC-06 | B7: Login | C7: Locked account auto-unlocks after lockout window expires | D7: Positive | E7: unauthenticated | F7: A user is_locked=true with locked_until already in the past. | G7: 1) POST /api/v1/auth/login with that user's correct credentials. | H7: 200 OK. Login succeeds; is_locked reset to false, locked_until cleared, failed_login_count reset to 0; tokens returned.
A8: SEC-07 | B8: Refresh Token | C8: Refresh with valid refresh token issues new access token | D8: Positive | E8: any-authenticated | F8: User logged in and holds a valid refresh_token; user is_active=true. | G8: 1) POST /api/v1/auth/refresh with {"refresh_token":"<valid refresh token>"}. | H8: 200 OK. Body contains a new access_token and token_type="bearer".
A9: SEC-08 | B9: Refresh Token | C9: Refresh rejects an access token used as refresh token | D9: Negative | E9: any-authenticated | F9: A valid access token (type=access) is available. | G9: 1) POST /api/v1/auth/refresh with the access token as refresh_token. | H9: 401 Unauthorized, detail="Invalid refresh token" (token type != "refresh").
A10: SEC-09 | B10: Refresh Token | C10: Refresh with garbage/expired token rejected | D10: Negative | E10: unauthenticated | F10: None. | G10: 1) POST /api/v1/auth/refresh with {"refresh_token":"not.a.jwt"}. | H10: 401 Unauthorized, detail="Invalid refresh token" (decode_token returns None).
A11: SEC-10 | B11: Get Me | C11: GET /auth/me returns the current authenticated user | D11: Positive | E11: any-authenticated | F11: Valid access token for an active user. | G11: 1) GET /api/v1/auth/me with Authorization: Bearer <access token>. | H11: 200 OK with id, username, full_name, email, role, page_permissions of the logged-in user.
A12: SEC-11 | B12: Get Me | C12: GET /auth/me after force-logout/suspension is invalidated | D12: Negative | E12: any-authenticated | F12: User had a valid access token but has since been suspended (is_active=false). | G12: 1) GET /api/v1/auth/me using the previously valid access token. | H12: 401 Unauthorized. Because get_current_user filters is_active==True, the dependency itself fails with detail="Could not validate credentials" (the inner re-fetch "Session invalidated" check applies when token is still valid but user row is inactive).
A13: SEC-12 | B13: Get Me | C13: GET /auth/me without token is rejected | D13: Negative | E13: unauthenticated | F13: None. | G13: 1) GET /api/v1/auth/me with no Authorization header. | H13: 401 Unauthorized (OAuth2 scheme: "Not authenticated").
... A61: SEC-60 | B61: Warehouse Scoping | C61: Warehouse-mapped non-super_admin sees only mapped Delivery Challans | D61: Positive | E61: sales | F61: A non-super_admin user has restrict_to_warehouse_id / warehouse_id set to warehouse W; delivery challans exist for W and for another warehouse. | G61: 1) Log in as the warehouse-mapped user. 2) List delivery challans. | H61: Only delivery challans belonging to warehouse W are visible; challans from other warehouses are hidden. (A super_admin sees all warehouses.)

Sheet SET Settings
A1: ID | B1: Area | C1: Title | D1: Type | E1: Role | F1: Pre-condition | G1: Steps | H1: Expected | I1: Pass/Fail | J1: Notes
A2: SET-01 | B2: Get Company Settings | C2: Fetch company settings as authenticated user | D2: Positive | E2: any-authenticated | F2: A CompanySettings row exists in DB. Valid bearer token (e.g. admin/Admin@1234). | G2: 1) GET /api/v1/settings/company with Authorization: Bearer <token> | H2: 200 OK. JSON object with id, company_name, gstin, state, state_code, prefixes (b2b_invoice_prefix, b2c_invoice_prefix, quotation_prefix, challan_prefix, credit_note_prefix), eway_threshold, bank_stock_margin, financial_year_start, logo_path, signature_path, and bank_* / upi_id fields reflecting stored values.
A3: SET-02 | B3: Get Company Settings | C3: Default settings returned when no row exists | D3: Positive | E3: any-authenticated | F3: CompanySettings table is empty (no row). Valid bearer token. | G3: 1) GET /api/v1/settings/company | H3: 200 OK with defaults: id=null, company_name="My Wholesale Company", b2b_invoice_prefix="BINV", b2c_invoice_prefix="CINV", quotation_prefix="QT", challan_prefix="DC", credit_note_prefix="CN", eway_threshold=50000, bank_stock_margin=25.00, financial_year_start=4.
A4: SET-03 | B4: Get Company Settings | C4: Unauthenticated request to company settings | D4: Negative | E4: unauthenticated | F4: No Authorization header. | G4: 1) GET /api/v1/settings/company with no token | H4: 401 Unauthorized. detail="Not authenticated" (missing token) or "Could not validate credentials" for invalid token; WWW-Authenticate: Bearer header present.
A5: SET-04 | B5: Update Company Settings | C5: Admin updates existing company settings | D5: Positive | E5: admin | F5: CompanySettings row exists. Logged in as admin or super_admin. | G5: 1) PUT /api/v1/settings/company with body {"company_name":"Acme Traders","gstin":"29ABCDE1234F1Z5","state":"Karnataka","state_code":29,"eway_threshold":50000} | H5: 200 OK. Response reflects updated company_name="Acme Traders", gstin, state_code=29. updated_by set to current user. Fields omitted from payload (exclude_none) are left unchanged.
A6: SET-05 | B6: Update Company Settings | C6: Update creates settings row when none exists | D6: Positive | E6: admin | F6: CompanySettings table empty. Logged in as admin. | G6: 1) PUT /api/v1/settings/company with body {"company_name":"New Co","state_code":27} | H6: 200 OK. New CompanySettings row created with company_name="New Co", state_code=27, created_by=current user; unsupplied defaults applied (gstin="", state="", address_line1="", city="", pincode=""). Response id is non-null.
A7: SET-06 | B7: Update Company Settings | C7: Partial update preserves untouched fields | D7: Positive | E7: admin | F7: CompanySettings row exists with gstin and bank details populated. Logged in as admin. | G7: 1) PUT /api/v1/settings/company with body {"phone":"9876543210"} | H7: 200 OK. Only phone updated to 9876543210; gstin, bank_name and all other previously-stored fields remain unchanged (exclude_none semantics).
A8: SET-07 | B8: Update Company Settings | C8: Accountant forbidden from updating company settings | D8: Negative | E8: accountant | F8: Logged in as a user with role=accountant. | G8: 1) PUT /api/v1/settings/company with any valid body | H8: 403 Forbidden. detail="Admin access required" (require_admin).
A9: SET-08 | B9: Update Company Settings | C9: Sales role forbidden from updating company settings | D9: Negative | E9: sales | F9: Logged in as a user with role=sales. | G9: 1) PUT /api/v1/settings/company with body {"company_name":"X"} | H9: 403 Forbidden. detail="Admin access required".
A10: SET-09 | B10: Update Company Settings | C10: Unauthenticated update rejected | D10: Negative | E10: unauthenticated | F10: No token. | G10: 1) PUT /api/v1/settings/company with body {"company_name":"X"} and no Authorization header | H10: 401 Unauthorized. detail="Not authenticated".
A11: SET-10 | B11: Update Company Settings | C11: Invalid type for numeric field rejected | D11: Negative | E11: admin | F11: Logged in as admin. | G11: 1) PUT /api/v1/settings/company with body {"state_code":"abc"} | H11: 422 Unprocessable Entity. Pydantic validation error on state_code (int_parsing) — body is not committed.
A12: SET-11 | B12: Update Company Settings | C12: Invalid type for eway_threshold decimal rejected | D12: Negative | E12: admin | F12: Logged in as admin. | G12: 1) PUT /api/v1/settings/company with body {"eway_threshold":"not-a-number"} | H12: 422 Unprocessable Entity. Pydantic decimal_parsing error on eway_threshold.
A13: SET-12 | B13: Get Invoice Sequences | C13: List invoice sequences as authenticated user | D13: Positive | E13: any-authenticated | F13: At least one InvoiceSequence row exists (created by seed.py). Valid token. | G13: 1) GET /api/v1/settings/invoice-sequences | H13: 200 OK. JSON array; each item has id, document_type, prefix, financial_year, last_number.
... A36: SET-35 | B36: Update User Permissions | C36: Non-admin forbidden from updating permissions | D36: Negative | E36: accountant | F36: A sales user exists. Logged in as accountant. | G36: 1) PUT /api/v1/settings/users-permissions/<sales_id> with body {"page_permissions":["billing"]} | H36: 403 Forbidden. detail="Admin access required" (require_admin).
